{"config_index.md":"9b915125","guide_badges.md":"da855aed","guide_examples.md":"b1ee3034","guide_hooks.md":"887c16b6","guide_index.md":"242a589b","guide_injected_languages.md":"8cf046bb","guide_installation.md":"fc2dc73d","guide_installation_cli.md":"fda1da3a","guide_installation_docker.md":"2f545ae1","guide_installation_vscode.md":"c949fe56","guide_environments.md":"f08f8709","guide_response.md":"d647b9d0","guide_scripting.md":"7f0e89a4","guide_troubleshooting.md":"036efd0d","index.md":"604d97a7","plugins_index.md":"041d8f32","guide_metadata.md":"367206a1","guide_installation_httpbook.md":"a082c266","plugins_plugin-api.md":"4b287d1f","guide_comment.md":"b12d5904","guide_request.md":"4f86a686","guide_variables.md":"90db4a11"}
